discordDB/__init__.py
discordDB/db.py
discordDB/models/__init__.py
discordDB/models/types.py
DiscordDB-0.0.6.dist-info/LICENSE
DiscordDB-0.0.6.dist-info/METADATA
DiscordDB-0.0.6.dist-info/WHEEL
DiscordDB-0.0.6.dist-info/top_level.txt
DiscordDB-0.0.6.dist-info/RECORD
